{
    "result": {
        "NQU1-NQH2": [
            {
                "d0": "2020-12-06",
                "d1": "2021-10-03",
                "s": "23177"
            }
        ],
        "NQZ0-NQM1": [
            {
                "d0": "2020-07-17",
                "d1": "2021-01-03",
                "s": "20982"
            }
        ],
        "NQZ4": [
            {
                "d0": "2022-05-22",
                "d1": "2025-07-18",
                "s": "106364"
            }
        ],
        "NQU0-NQM1": [
            {
                "d0": "2020-07-17",
                "d1": "2020-10-04",
                "s": "20973"
            }
        ],
        "NQM5-NQM6": [
            {
                "d0": "2025-03-09",
                "d1": "2025-06-29",
                "s": "42017745"
            }
        ],
        "NQZ0-NQU1": [
            {
                "d0": "2020-07-17",
                "d1": "2021-01-03",
                "s": "4545"
            }
        ],
        "NQH4-NQM4": [
            {
                "d0": "2023-03-05",
                "d1": "2025-07-18",
                "s": "19066"
            }
        ],
        "NQH2-NQU2": [
            {
                "d0": "2021-06-06",
                "d1": "2022-03-22",
                "s": "19924"
            }
        ],
        "NQH5-NQH6": [
            {
                "d0": "2024-12-08",
                "d1": "2025-03-30",
                "s": "42017606"
            }
        ],
        "NQZ5-NQH6": [
            {
                "d0": "2024-12-08",
                "d1": "2025-07-18",
                "s": "42006122"
            }
        ],
        "NQM4-NQU4": [
            {
                "d0": "2023-06-06",
                "d1": "2025-07-18",
                "s": "9947"
            }
        ],
        "NQH2-NQM2": [
            {
                "d0": "2021-03-07",
                "d1": "2022-03-22",
                "s": "15986"
            }
        ],
        "NQH5-NQM5": [
            {
                "d0": "2024-03-03",
                "d1": "2025-03-30",
                "s": "42028228"
            }
        ],
        "NQM1-NQM2": [
            {
                "d0": "2021-03-07",
                "d1": "2021-07-04",
                "s": "16343"
            }
        ],
        "NQM1-NQU1": [
            {
                "d0": "2020-07-17",
                "d1": "2021-07-04",
                "s": "10903"
            }
        ],
        "NQM4-NQM5": [
            {
                "d0": "2024-03-03",
                "d1": "2024-06-30",
                "s": "42028185"
            }
        ],
        "NQH4-NQH5": [
            {
                "d0": "2023-12-03",
                "d1": "2024-03-24",
                "s": "42024867"
            }
        ],
        "NQM2-NQM3": [
            {
                "d0": "2022-03-06",
                "d1": "2022-06-26",
                "s": "20011"
            }
        ],
        "NQM1-NQZ1": [
            {
                "d0": "2020-09-06",
                "d1": "2021-07-04",
                "s": "19685"
            }
        ],
        "NQH5-NQU5": [
            {
                "d0": "2024-06-09",
                "d1": "2025-03-30",
                "s": "42006418"
            }
        ],
        "NQU4-NQM5": [
            {
                "d0": "2024-03-03",
                "d1": "2024-09-29",
                "s": "42021115"
            }
        ],
        "NQH3-NQM3": [
            {
                "d0": "2022-03-06",
                "d1": "2023-03-26",
                "s": "19669"
            }
        ],
        "NQM5-NQU5": [
            {
                "d0": "2024-06-09",
                "d1": "2025-06-29",
                "s": "42009338"
            }
        ],
        "NQM4": [
            {
                "d0": "2023-03-05",
                "d1": "2025-07-18",
                "s": "13743"
            }
        ],
        "NQU5-NQM6": [
            {
                "d0": "2025-03-09",
                "d1": "2025-07-18",
                "s": "42017750"
            }
        ],
        "NQH6-NQU6": [
            {
                "d0": "2025-06-08",
                "d1": "2025-07-18",
                "s": "42018378"
            }
        ],
        "NQU5": [
            {
                "d0": "2024-03-03",
                "d1": "2025-07-18",
                "s": "42008487"
            }
        ],
        "NQM5-NQZ5": [
            {
                "d0": "2024-09-08",
                "d1": "2025-06-29",
                "s": "42005291"
            }
        ],
        "NQM6": [
            {
                "d0": "2024-12-08",
                "d1": "2025-07-18",
                "s": "42004058"
            }
        ],
        "NQZ0": [
            {
                "d0": "2020-07-17",
                "d1": "2021-01-03",
                "s": "16337"
            },
            {
                "d0": "2025-06-08",
                "d1": "2025-07-18",
                "s": "42005663"
            }
        ],
        "NQZ7": [
            {
                "d0": "2022-09-04",
                "d1": "2025-07-18",
                "s": "23041"
            }
        ],
        "NQZ3-NQZ4": [
            {
                "d0": "2023-09-03",
                "d1": "2023-12-24",
                "s": "42036223"
            }
        ],
        "NQZ9": [
            {
                "d0": "2024-06-09",
                "d1": "2025-07-18",
                "s": "42001830"
            }
        ],
        "NQM3-NQM4": [
            {
                "d0": "2023-03-05",
                "d1": "2025-07-18",
                "s": "19040"
            }
        ],
        "NQZ3": [
            {
                "d0": "2022-05-22",
                "d1": "2025-07-18",
                "s": "260937"
            }
        ],
        "NQZ5-NQM6": [
            {
                "d0": "2025-03-09",
                "d1": "2025-07-18",
                "s": "42014438"
            }
        ],
        "NQU4-NQH5": [
            {
                "d0": "2023-12-03",
                "d1": "2024-09-29",
                "s": "42031058"
            }
        ],
        "NQU2-NQU3": [
            {
                "d0": "2022-06-07",
                "d1": "2022-09-25",
                "s": "3560"
            }
        ],
        "NQZ0-NQH1": [
            {
                "d0": "2020-07-17",
                "d1": "2021-01-03",
                "s": "18275"
            }
        ],
        "NQU0-NQU1": [
            {
                "d0": "2020-07-17",
                "d1": "2020-10-04",
                "s": "7990"
            }
        ],
        "NQH5-NQZ5": [
            {
                "d0": "2024-09-08",
                "d1": "2025-03-30",
                "s": "42007724"
            }
        ],
        "NQH3-NQZ3": [
            {
                "d0": "2022-09-04",
                "d1": "2023-03-26",
                "s": "42738"
            }
        ],
        "NQM3": [
            {
                "d0": "2022-03-06",
                "d1": "2025-07-18",
                "s": "3522"
            }
        ],
        "NQM3-NQH4": [
            {
                "d0": "2022-12-04",
                "d1": "2025-07-18",
                "s": "16813"
            }
        ],
        "NQU5-NQH6": [
            {
                "d0": "2024-12-08",
                "d1": "2025-07-18",
                "s": "42019267"
            }
        ],
        "NQZ2-NQM3": [
            {
                "d0": "2022-03-06",
                "d1": "2022-12-25",
                "s": "17339"
            }
        ],
        "NQZ1-NQM2": [
            {
                "d0": "2021-03-07",
                "d1": "2022-01-02",
                "s": "17779"
            }
        ],
        "NQH2": [
            {
                "d0": "2020-12-06",
                "d1": "2022-03-22",
                "s": "3541"
            }
        ],
        "NQU6": [
            {
                "d0": "2025-03-09",
                "d1": "2025-07-18",
                "s": "42004177"
            }
        ],
        "NQH6-NQM6": [
            {
                "d0": "2025-03-09",
                "d1": "2025-07-18",
                "s": "42014562"
            }
        ],
        "NQU2-NQH3": [
            {
                "d0": "2021-12-05",
                "d1": "2022-09-25",
                "s": "39215"
            }
        ],
        "NQU3-NQM4": [
            {
                "d0": "2023-03-05",
                "d1": "2025-07-18",
                "s": "19053"
            }
        ],
        "NQM6-NQU6": [
            {
                "d0": "2025-06-08",
                "d1": "2025-07-18",
                "s": "42012025"
            }
        ],
        "NQU4": [
            {
                "d0": "2023-06-04",
                "d1": "2025-07-18",
                "s": "4358"
            }
        ],
        "NQU0": [
            {
                "d0": "2020-07-17",
                "d1": "2020-10-04",
                "s": "14028"
            }
        ],
        "NQH4-NQU4": [
            {
                "d0": "2023-06-06",
                "d1": "2025-07-18",
                "s": "9925"
            }
        ],
        "NQM2-NQH3": [
            {
                "d0": "2021-12-05",
                "d1": "2022-06-26",
                "s": "39081"
            }
        ],
        "NQU3": [
            {
                "d0": "2022-06-05",
                "d1": "2025-07-18",
                "s": "2130"
            }
        ],
        "NQZ8": [
            {
                "d0": "2023-09-03",
                "d1": "2025-07-18",
                "s": "42030720"
            }
        ],
        "NQZ2-NQZ3": [
            {
                "d0": "2022-09-04",
                "d1": "2022-12-25",
                "s": "40549"
            }
        ],
        "NQZ2": [
            {
                "d0": "2021-09-05",
                "d1": "2022-12-25",
                "s": "13613"
            }
        ],
        "NQZ2-NQH3": [
            {
                "d0": "2021-12-05",
                "d1": "2022-12-25",
                "s": "39253"
            }
        ],
        "NQM2": [
            {
                "d0": "2021-03-07",
                "d1": "2022-06-26",
                "s": "2895"
            }
        ],
        "NQU5-NQZ5": [
            {
                "d0": "2024-09-08",
                "d1": "2025-07-18",
                "s": "42005997"
            }
        ],
        "NQH4": [
            {
                "d0": "2022-12-04",
                "d1": "2025-07-18",
                "s": "750"
            }
        ],
        "NQU2": [
            {
                "d0": "2021-06-06",
                "d1": "2022-09-25",
                "s": "10391"
            }
        ],
        "NQZ0-NQZ1": [
            {
                "d0": "2020-09-06",
                "d1": "2021-01-03",
                "s": "20862"
            }
        ],
        "NQZ5-NQU6": [
            {
                "d0": "2025-06-08",
                "d1": "2025-07-18",
                "s": "42012003"
            }
        ],
        "NQH5": [
            {
                "d0": "2023-11-16",
                "d1": "2025-03-30",
                "s": "42288528"
            }
        ],
        "NQM5-NQH6": [
            {
                "d0": "2024-12-08",
                "d1": "2025-06-29",
                "s": "42006097"
            }
        ],
        "NQZ3-NQH4": [
            {
                "d0": "2022-12-04",
                "d1": "2025-07-18",
                "s": "14933"
            }
        ],
        "NQZ4-NQU5": [
            {
                "d0": "2024-06-09",
                "d1": "2024-12-29",
                "s": "42004691"
            }
        ],
        "NQM3-NQU3": [
            {
                "d0": "2022-06-07",
                "d1": "2025-07-18",
                "s": "1584"
            }
        ],
        "NQU0-NQH1": [
            {
                "d0": "2020-07-17",
                "d1": "2020-10-04",
                "s": "18315"
            }
        ],
        "NQH1-NQM1": [
            {
                "d0": "2020-07-17",
                "d1": "2021-04-04",
                "s": "20987"
            }
        ],
        "NQH1-NQU1": [
            {
                "d0": "2020-07-17",
                "d1": "2021-04-04",
                "s": "10351"
            }
        ],
        "NQU0-NQZ0": [
            {
                "d0": "2020-07-17",
                "d1": "2020-10-04",
                "s": "14523"
            }
        ],
        "NQM3-NQZ3": [
            {
                "d0": "2022-09-04",
                "d1": "2025-07-18",
                "s": "46494"
            }
        ],
        "NQU1-NQU2": [
            {
                "d0": "2021-06-06",
                "d1": "2021-10-03",
                "s": "23381"
            }
        ],
        "NQM1-NQH2": [
            {
                "d0": "2020-12-06",
                "d1": "2021-07-04",
                "s": "18134"
            }
        ],
        "NQZ4-NQZ5": [
            {
                "d0": "2024-09-08",
                "d1": "2024-12-29",
                "s": "42005979"
            }
        ],
        "NQH6": [
            {
                "d0": "2024-09-08",
                "d1": "2025-07-18",
                "s": "42002475"
            }
        ],
        "NQU1": [
            {
                "d0": "2020-07-17",
                "d1": "2021-10-03",
                "s": "828"
            }
        ],
        "NQM5": [
            {
                "d0": "2023-12-03",
                "d1": "2025-06-29",
                "s": "42005804"
            }
        ],
        "NQZ3-NQU4": [
            {
                "d0": "2023-06-06",
                "d1": "2025-07-18",
                "s": "16093"
            }
        ],
        "NQM2-NQU2": [
            {
                "d0": "2021-06-06",
                "d1": "2022-06-26",
                "s": "22876"
            }
        ],
        "NQH3-NQU3": [
            {
                "d0": "2022-06-07",
                "d1": "2023-03-26",
                "s": "3564"
            }
        ],
        "NQU2-NQM3": [
            {
                "d0": "2022-03-06",
                "d1": "2022-09-25",
                "s": "17329"
            }
        ],
        "NQH2-NQZ2": [
            {
                "d0": "2021-09-05",
                "d1": "2022-03-22",
                "s": "22643"
            }
        ],
        "NQH1-NQH2": [
            {
                "d0": "2020-12-06",
                "d1": "2021-04-04",
                "s": "21053"
            }
        ],
        "NQM4-NQZ4": [
            {
                "d0": "2023-09-03",
                "d1": "2024-06-30",
                "s": "42035278"
            }
        ],
        "NQH2-NQH3": [
            {
                "d0": "2021-12-05",
                "d1": "2022-03-22",
                "s": "32884"
            }
        ],
        "NQZ4-NQM5": [
            {
                "d0": "2024-03-03",
                "d1": "2024-12-29",
                "s": "42036618"
            }
        ],
        "NQZ1-NQU2": [
            {
                "d0": "2021-06-06",
                "d1": "2022-01-02",
                "s": "23393"
            }
        ],
        "NQZ5": [
            {
                "d0": "2022-05-22",
                "d1": "2025-07-18",
                "s": "158704"
            }
        ],
        "NQZ2-NQU3": [
            {
                "d0": "2022-06-07",
                "d1": "2022-12-25",
                "s": "4374"
            }
        ],
        "NQZ1-NQZ2": [
            {
                "d0": "2021-09-05",
                "d1": "2022-01-02",
                "s": "29432"
            }
        ],
        "NQZ1-NQH2": [
            {
                "d0": "2020-12-06",
                "d1": "2022-01-02",
                "s": "23200"
            }
        ],
        "NQZ4-NQH5": [
            {
                "d0": "2023-12-03",
                "d1": "2024-12-29",
                "s": "42029580"
            }
        ],
        "NQM1": [
            {
                "d0": "2020-07-17",
                "d1": "2021-07-04",
                "s": "2786"
            }
        ],
        "NQU3-NQH4": [
            {
                "d0": "2022-12-04",
                "d1": "2025-07-18",
                "s": "10738"
            }
        ],
        "NQU2-NQZ2": [
            {
                "d0": "2021-09-05",
                "d1": "2022-11-10",
                "s": "26869"
            }
        ],
        "NQH3-NQH4": [
            {
                "d0": "2022-12-04",
                "d1": "2023-05-16",
                "s": "14895"
            }
        ],
        "NQM2-NQZ2": [
            {
                "d0": "2021-09-05",
                "d1": "2022-06-26",
                "s": "26850"
            }
        ],
        "NQH3": [
            {
                "d0": "2021-12-05",
                "d1": "2023-03-26",
                "s": "20631"
            }
        ],
        "NQH1": [
            {
                "d0": "2020-07-17",
                "d1": "2021-04-04",
                "s": "4378"
            }
        ],
        "NQZ1": [
            {
                "d0": "2020-09-06",
                "d1": "2022-01-02",
                "s": "2770"
            }
        ],
        "NQU5-NQU6": [
            {
                "d0": "2025-06-08",
                "d1": "2025-07-18",
                "s": "42010220"
            }
        ],
        "NQM4-NQH5": [
            {
                "d0": "2023-12-03",
                "d1": "2024-06-30",
                "s": "42012843"
            }
        ],
        "NQU3-NQU4": [
            {
                "d0": "2023-06-06",
                "d1": "2025-07-18",
                "s": "9011"
            }
        ],
        "NQZ6": [
            {
                "d0": "2022-05-22",
                "d1": "2025-07-18",
                "s": "261401"
            }
        ],
        "NQU4-NQU5": [
            {
                "d0": "2024-06-09",
                "d1": "2024-09-29",
                "s": "42007509"
            }
        ],
        "NQH1-NQZ1": [
            {
                "d0": "2020-09-06",
                "d1": "2021-04-04",
                "s": "18204"
            }
        ],
        "NQZ3-NQM4": [
            {
                "d0": "2023-03-05",
                "d1": "2025-07-18",
                "s": "18566"
            }
        ],
        "NQU1-NQM2": [
            {
                "d0": "2021-03-07",
                "d1": "2021-10-03",
                "s": "20705"
            }
        ],
        "NQU1-NQZ1": [
            {
                "d0": "2020-09-06",
                "d1": "2021-10-03",
                "s": "20370"
            }
        ],
        "NQH4-NQZ4": [
            {
                "d0": "2023-09-03",
                "d1": "2024-03-24",
                "s": "42035277"
            }
        ],
        "NQU3-NQZ3": [
            {
                "d0": "2022-09-04",
                "d1": "2025-07-18",
                "s": "40618"
            }
        ],
        "NQU4-NQZ4": [
            {
                "d0": "2023-09-03",
                "d1": "2024-09-29",
                "s": "42036224"
            }
        ]
    },
    "symbols": [
        "NQ.FUT"
    ],
    "stype_in": "parent",
    "stype_out": "instrument_id",
    "start_date": "2020-07-18",
    "end_date": "2025-07-18",
    "partial": [
        "NQU1-NQH2",
        "NQZ4",
        "NQM5-NQM6",
        "NQH4-NQM4",
        "NQH2-NQU2",
        "NQH5-NQH6",
        "NQZ5-NQH6",
        "NQM4-NQU4",
        "NQH2-NQM2",
        "NQH5-NQM5",
        "NQM1-NQM2",
        "NQM4-NQM5",
        "NQH4-NQH5",
        "NQM2-NQM3",
        "NQM1-NQZ1",
        "NQH5-NQU5",
        "NQU4-NQM5",
        "NQH3-NQM3",
        "NQM5-NQU5",
        "NQM4",
        "NQU5-NQM6",
        "NQH6-NQU6",
        "NQU5",
        "NQM5-NQZ5",
        "NQM6",
        "NQZ0",
        "NQZ7",
        "NQZ3-NQZ4",
        "NQZ9",
        "NQM3-NQM4",
        "NQZ3",
        "NQZ5-NQM6",
        "NQU4-NQH5",
        "NQU2-NQU3",
        "NQH5-NQZ5",
        "NQH3-NQZ3",
        "NQM3",
        "NQM3-NQH4",
        "NQU5-NQH6",
        "NQZ2-NQM3",
        "NQZ1-NQM2",
        "NQH2",
        "NQU6",
        "NQH6-NQM6",
        "NQU2-NQH3",
        "NQU3-NQM4",
        "NQM6-NQU6",
        "NQU4",
        "NQH4-NQU4",
        "NQM2-NQH3",
        "NQU3",
        "NQZ8",
        "NQZ2-NQZ3",
        "NQZ2",
        "NQZ2-NQH3",
        "NQM2",
        "NQU5-NQZ5",
        "NQH4",
        "NQU2",
        "NQZ0-NQZ1",
        "NQZ5-NQU6",
        "NQH5",
        "NQM5-NQH6",
        "NQZ3-NQH4",
        "NQZ4-NQU5",
        "NQM3-NQU3",
        "NQM3-NQZ3",
        "NQU1-NQU2",
        "NQM1-NQH2",
        "NQZ4-NQZ5",
        "NQH6",
        "NQM5",
        "NQZ3-NQU4",
        "NQM2-NQU2",
        "NQH3-NQU3",
        "NQU2-NQM3",
        "NQH2-NQZ2",
        "NQH1-NQH2",
        "NQM4-NQZ4",
        "NQH2-NQH3",
        "NQZ4-NQM5",
        "NQZ1-NQU2",
        "NQZ5",
        "NQZ2-NQU3",
        "NQZ1-NQZ2",
        "NQZ1-NQH2",
        "NQZ4-NQH5",
        "NQU3-NQH4",
        "NQU2-NQZ2",
        "NQH3-NQH4",
        "NQM2-NQZ2",
        "NQH3",
        "NQZ1",
        "NQU5-NQU6",
        "NQM4-NQH5",
        "NQU3-NQU4",
        "NQZ6",
        "NQU4-NQU5",
        "NQH1-NQZ1",
        "NQZ3-NQM4",
        "NQU1-NQM2",
        "NQU1-NQZ1",
        "NQH4-NQZ4",
        "NQU3-NQZ3",
        "NQU4-NQZ4"
    ],
    "not_found": [],
    "message": "Partially resolved",
    "status": 1
}